poof/__init__.py
poof/launchd.py
poof/v2.py
grogu-0.0.0.dist-info/LICENSE.txt
grogu-0.0.0.dist-info/METADATA
grogu-0.0.0.dist-info/WHEEL
grogu-0.0.0.dist-info/entry_points.txt
grogu-0.0.0.dist-info/namespace_packages.txt
grogu-0.0.0.dist-info/top_level.txt
grogu-0.0.0.dist-info/RECORD
