Metadata-Version: 2.1
Name: grogu
Version: 0.0.0
Summary: poof backup - instant, secure backup to a cloud drive
Home-page: https://github.com/poof-backup/poof
Author: Eugene Ciurana pr3d4t0r
Author-email: poof.project@cime.net
License: BSD3
Platform: UNKNOWN
Classifier: Intended Audience :: Other Audience
Classifier: License :: OSI Approved :: BSD License
Classifier: Operating System :: MacOS
Classifier: Operating System :: Unix
Classifier: Programming Language :: Python :: 3
Classifier: Programming Language :: Python :: 3.7
Classifier: Topic :: System :: Archiving :: Backup
Classifier: Topic :: Utilities
License-File: LICENSE.txt
Requires-Dist: appdirs
Requires-Dist: click
Requires-Dist: psutil
Requires-Dist: pyperclip
